[
  {
   "FirstName": "uqwiiIQO%A",
    "MiddleName": "C+rGPFRtYV",
    "Lastname": "yh@18ZlD)k",
    "Nickname": ")HaeL3y5O^",
    "Company": "X5d*M7-iSh",
    "Title": "I_HYAM2)xJ",
    "Address": "uMSdF(uN(j",
    "HomePhone": "fkfh=*E*pA",
    "MobilePhone": "aD9mc--Be-",
    "WorkPhone": "A2HEULnA#R",
    "Fax": "M9o6BwpyaH",
    "Email1": "I9ex7ra3BF",
    "Email2": ")s6(j0caM!",
    "Email3": "eDFX@omCk3",
    "Homepage": "iZzW^PYiV1",
    "Birthday": "88-7WrDtXZ",
    "MonthOfBirth": "April",
    "YearhOfBirth": "Olo1E4G9TE",
    "AnniversaryDay": "YSVvt*kCUb",
    "MonthOfAnniversary": "December",
    "YearOfAnniversary": "FjBtEWATl*",
    "SecondaryAddress": "3LjT@Lt@iS",
    "SecondaryHomePhone": "wCwkq1L1yq",
    "Notes": "qC=aJCmH-i",
  },
  {
    "FirstName": "Fq5LsG!b56",
    "MiddleName": "%P9JVD@pDb",
    "Lastname": "KXt(a0MJK9",
    "Nickname": "wm@AMGUk^j",
    "Company": "^8)^0bR$EG",
    "Title": "P_DwX5_@9&",
    "Address": "(0R_Jcc8_P",
    "HomePhone": "6ayskac1R-",
    "MobilePhone": "jWEEt0iP0e",
    "WorkPhone": "Jgz-oOr=5Y",
    "Fax": "-g*$X$WiL+",
    "Email1": "dSt!hvvMah",
    "Email2": "*MHpFazyEW",
    "Email3": "6d_*ACdP44",
    "Homepage": "eAD3B^!#q*",
    "Birthday": "qewYf!Zb8+",
    "MonthOfBirth": "March",
    "YearhOfBirth": "ve$O-W0!fR",
    "AnniversaryDay": "gfuC&JcnNn",
    "MonthOfAnniversary": "October",
    "YearOfAnniversary": "IL3c5vlN0C",
    "SecondaryAddress": "f7r6uNoBsK",
    "SecondaryHomePhone": "CLzJ=CVn1+",
    "Notes": "@uhbmTJ9Sz",
  },
  {
    "FirstName": "Pw2PBwDUW)",
    "MiddleName": "@mtd8+jue3",
    "Lastname": "Z=k3O8aPUa",
    "Nickname": "D26*(dgjIa",
    "Company": "-BQ5JZBEqo",
    "Title": "7nfnZQM=BQ",
    "Address": "V@-)^J3zie",
    "HomePhone": "p-mE3X52u#",
    "MobilePhone": "7Vw3roWTs2",
    "WorkPhone": "Rii^EMBV$A",
    "Fax": "uZuM-8Bb7B",
    "Email1": "iicMhAOUcb",
    "Email2": "!jH3NGou-r",
    "Email3": "Vk#tShzk36",
    "Homepage": "m)jqT7FWiE",
    "Birthday": "=5*mOKS%-&",
    "MonthOfBirth": "April",
    "YearhOfBirth": "ebP3=t6*-Y",
    "AnniversaryDay": "1ot$%AokdB",
    "MonthOfAnniversary": "March",
    "YearOfAnniversary": "M)torafIO9",
    "SecondaryAddress": "k@nHrT@VNX",
    "SecondaryHomePhone": "ci3URXxXJ2",
    "Notes": "dt^BSguPfT",
  }
]